setup.py
protocyt/ProtobufGrammar.txt
protocyt/__init__.py
protocyt/classes.py
protocyt/common.pytempl
protocyt/compiler.py
protocyt/file.pytempl
protocyt/message.pytempl
protocyt/meta.py
protocyt/package.pytempl
protocyt/parser.py
protocyt/path.py
protocyt/protoc.py
protocyt/record.py
protocyt/structure.pytempl
protocyt/templatable.py
protocyt.egg-info/PKG-INFO
protocyt.egg-info/SOURCES.txt
protocyt.egg-info/dependency_links.txt
protocyt.egg-info/requires.txt
protocyt.egg-info/top_level.txt
protocyt/includes/stdint.h