Metadata-Version: 1.1
Name: protocyt
Version: 0.1.5
Summary: Fast python port of protobuf
Home-page: http://evgenus.github.com/protocyt/
Author: Eugene Chernyshov
Author-email: Chernyshov.Eugene@gmail.com
License: LGPL
Keywords: serialization data-format cython protobuf
Platform: UNKNOWN
Classifier: Development Status :: 4 - Beta
Classifier: License :: OSI Approved :: GNU Library or Lesser General Public License (LGPL)
Classifier: Operating System :: OS Independent
Classifier: Topic :: Internet
Classifier: Programming Language :: Python
